dash_redux/__init__.py
dash_redux/_version.py
dash_redux/redux_store.py
todo/__init__.py
todo/todo.py
todo/todo_model.py
dash_redux-0.0.5.dist-info/LICENSE
dash_redux-0.0.5.dist-info/METADATA
dash_redux-0.0.5.dist-info/WHEEL
dash_redux-0.0.5.dist-info/top_level.txt
dash_redux-0.0.5.dist-info/RECORD
