Metadata-Version: 2.1
Name: dash-redux
Version: 0.0.5
Summary: Provides Plotly/Dash with support for a Redux style store of truth
Home-page: https://github.com/stevej2608/dash-redux
Author: Steve Jones
Author-email: jonesst608@gmail.com
License: MIT
Platform: UNKNOWN
Classifier: Development Status :: 2 - Pre-Alpha
Classifier: License :: OSI Approved :: MIT License
Classifier: Programming Language :: Python
Classifier: Programming Language :: Python :: 3.6
Classifier: Programming Language :: Python :: 3.7
Requires-Dist: dash (>=2.1.0)
Requires-Dist: dash-prefix (>=0.0.4)
